faktory/__init__.py
faktory/_proto.py
faktory/client.py
faktory/exceptions.py
faktory/worker.py
faktory-1.0.0.dist-info/LICENSE
faktory-1.0.0.dist-info/METADATA
faktory-1.0.0.dist-info/WHEEL
faktory-1.0.0.dist-info/top_level.txt
faktory-1.0.0.dist-info/RECORD
